[{"encoded_sent": [], "head_ent_type": "ORGANIZATION", "tail_ent_type": "NUMBER", "rewrited_sent": ["The", "US", "Department", "of", "Defense", "has", "an", "affiliation", "with", "the", "[[", "American", "Psychological", "Association", "]]", "containing", "148,000", "members", ",", "popularly", "known", "as", "Koochers", "K00KS", ".", "This", "relationship", "was", "reflected", "in", "the", "APA's", "Code", "of", "Ethics", "through", "the", "addition", "of", "Section", "1.02", ",", "often", "referred", "to", "as", "\"The", "Nuremberg", "Defense.", "\"", "Thus", ",", "the", "amended", "APA", "code", "of", "ethics", ",", "represented", "by", "the", "[[", "148,000", "members", "]]", "of", "the", "American", "Psychological", "Association", ",", "underlines", "their", "connection", "to", "the", "Department", "of", "Defense", "."], "head_ent": ["American", "Psychological", "Association"], "tail_ent": ["148,000"], "id": "org:number_of_employees--members_3_0"}, {"encoded_sent": [], "head_ent_type": "ORGANIZATION", "tail_ent_type": "NUMBER", "rewrited_sent": ["One", "of", "the", "largest", "importers", "of", "tropical", "fruit", "into", "Europe", "with", "a", "history", "dating", "back", "to", "a", "London", "banana", "importer", "in", "the", "1870s", ",", "is", "[[", "Fyffes", "]]", ".", "The", "company", "boasts", "a", "workforce", "of", "over", "[[", "4,800", "]]", "employees", "in", "11", "different", "countries", "."], "head_ent": ["Fyffes"], "tail_ent": ["4,800"], "id": "org:number_of_employees--members_3_1"}, {"encoded_sent": [], "head_ent_type": "ORGANIZATION", "tail_ent_type": "NUMBER", "rewrited_sent": ["Five", "Central", "American", "nations", "are", "represented", "through", "the", "[[", "Central", "American", "Parliament", "]]", ",", "comprising", "of", "[[", "132", "]]", "members", ",", "which", "was", "established", "in", "1986", "to", "facilitate", "political", "integration", "in", "the", "region", ",", "without", "infringing", "upon", "the", "authority", "of", "local", "legislatures", "."], "head_ent": ["Central", "American", "Parliament"], "tail_ent": ["132"], "id": "org:number_of_employees--members_3_2"}, {"encoded_sent": [], "head_ent_type": "ORGANIZATION", "tail_ent_type": "NUMBER", "rewrited_sent": ["The", "executive", "director", "of", "the", "[[", "Servicemembers", "Legal", "Defense", "Network", "]]", ",", "Aubrey", "Sarvis", ",", "attributed", "the", "resistance", "among", "the", "rank-and-file", "of", "the", "Army", "and", "Marines", "to", "the", "repeal", "of", "\"don't", "ask", ",", "don't", "tell", "\"", "in", "part", ",", "as", "his", "organization", "represents", "some", "of", "the", "[[", "approximately", "13,000", "]]", "gay", "men", "and", "lesbians", "who", "have", "been", "discharged", "from", "the", "military", "since", "the", "law's", "enactment", "."], "head_ent": ["Servicemembers", "Legal", "Defense", "Network"], "tail_ent": ["13,000"], "id": "org:number_of_employees--members_3_3"}, {"encoded_sent": [], "head_ent_type": "ORGANIZATION", "tail_ent_type": "NUMBER", "rewrited_sent": ["[[", "16,000", "employees", "]]", "work", "at", "[[", "Shenyang", "]]", ",", "established", "in", "1951", ",", "which", "is", "a", "renowned", "civilians", "and", "military", "aircraft", "manufacturing", "company", "collaborating", "with", "industry", "giants", "like", "Boeing", ",", "Airbus", ",", "Bombardier", ",", "Spirit", "AeroSystems", ",", "and", "Singapore", "Aerospace", "."], "head_ent": ["Shenyang"], "tail_ent": ["16,000"], "id": "org:number_of_employees--members_3_4"}, {"encoded_sent": [], "head_ent_type": "ORGANIZATION", "tail_ent_type": "NUMBER", "rewrited_sent": ["On", "five", "continents", ",", "there", "are", "over", "[[", "110", "]]", "staff", "members", "of", "the", "[[", "International", "Crisis", "Group", "]]", ",", "an", "independent", ",", "non-profit", "organization", ",", "who", "analyze", "conflict", "situations", "at", "the", "grassroots", "level", "and", "engage", "in", "advocacy", "at", "the", "highest", "level", "to", "prevent", "and", "resolve", "deadly", "conflicts", "."], "head_ent": ["International", "Crisis", "Group"], "tail_ent": ["110"], "id": "org:number_of_employees--members_3_5"}, {"encoded_sent": [], "head_ent_type": "ORGANIZATION", "tail_ent_type": "NUMBER", "rewrited_sent": ["The", "company", "[[", "IPSCO", "]]", ",", "with", "approximately", "[[", "4,400", "]]", "employees", ",", "reported", "a", "27", "%", "decrease", "in", "first-quarter", "net", "profit", "to", "$109.4", "million", "due", "to", "increased", "costs", ".", "Sales", "for", "the", "three-month", "period", ",", "however", ",", "increased", "by", "14", "%", "to", "reach", "$1.03", "billion", "."], "head_ent": ["IPSCO"], "tail_ent": ["4,400"], "id": "org:number_of_employees--members_3_6"}, {"encoded_sent": [], "head_ent_type": "ORGANIZATION", "tail_ent_type": "NUMBER", "rewrited_sent": ["Approximately", "750", "business", "units", "of", "[[", "The", "company", "]]", "are", "located", "in", "49", "different", "countries", ",", "and", "[[", "55,000", "]]", "individuals", "are", "part", "of", "its", "workforce", "."], "head_ent": ["The", "company"], "tail_ent": ["55,000"], "id": "org:number_of_employees--members_3_7"}, {"encoded_sent": [], "head_ent_type": "ORGANIZATION", "tail_ent_type": "NUMBER", "rewrited_sent": ["The", "estimated", "membership", "of", "the", "[[", "new", "Anglican", "Church", "in", "North", "America", "]]", "is", "approximately", "[[", "100,000", "]]", "individuals", "."], "head_ent": ["new", "Anglican", "Church", "in", "North", "America"], "tail_ent": ["100,000"], "id": "org:number_of_employees--members_3_8"}, {"encoded_sent": [], "head_ent_type": "ORGANIZATION", "tail_ent_type": "NUMBER", "rewrited_sent": ["[[", "IPSCO", ",", "an", "Illinois-based", "company", "]]", "has", "approximately", "4,400", "employees", "and", "can", "produce", "over", "4", "million", "tons", "of", "steel", "annually", ".", "Or", ",", "A", "steel", "manufacturing", "capacity", "exceeding", "4", "million", "tons", "is", "possessed", "by", "[[", "IPSCO", "]]", ",", "which", "is", "a", "company", "based", "in", "Illinois", ",", "and", "it", "employs", "approximately", "4,400", "people", "."], "head_ent": ["IPSCO"], "tail_ent": ["4,400"], "id": "org:number_of_employees--members_3_9"}, {"encoded_sent": [], "head_ent_type": "ORGANIZATION", "tail_ent_type": "NUMBER", "rewrited_sent": ["At", "[[", "Alcatel-Lucent", "]]", ",", "there", "are", "various", "domestic", "benefits", ",", "compensation", ",", "and", "executive", "compensation", "plans", "for", "[[", "22,000", "]]", "U.S", ".", "employees", "and", "over", "120,000", "retirees", "."], "head_ent": ["Alcatel-Lucent"], "tail_ent": ["22,000"], "id": "org:number_of_employees--members_3_10"}, {"encoded_sent": [], "head_ent_type": "ORGANIZATION", "tail_ent_type": "NUMBER", "rewrited_sent": ["The", "goody-bag", "tourism", "fund", ",", "amounting", "to", "$", "192", "million", "in", "the", "Senate's", "proposal", ",", "contrasts", "with", "the", "$", "342", "million", "allocated", "in", "the", "[[", "House", "]]", "budget", "\u2013", "a", "difference", "in", "representation", ",", "with", "40", "senators", "versus", "[[", "160", "]]", "representatives", ",", "resulting", "in", "fewer", "districts", "to", "cater", "to", "."], "head_ent": ["House"], "tail_ent": ["160"], "id": "org:number_of_employees--members_3_11"}, {"encoded_sent": [], "head_ent_type": "ORGANIZATION", "tail_ent_type": "NUMBER", "rewrited_sent": ["[[", "42,000", "]]", "employees", "work", "for", "[[", "Covidien", "]]", ",", "which", "generated", "over", "$10", "billion", "in", "revenue", "last", "year", "."], "head_ent": ["Covidien"], "tail_ent": ["42,000"], "id": "org:number_of_employees--members_3_12"}, {"encoded_sent": [], "head_ent_type": "ORGANIZATION", "tail_ent_type": "NUMBER", "rewrited_sent": ["A", "federal", "regulator's", "pen", "sweep", "will", "result", "in", "the", "addition", "of", "a", "new", "life-science", "industry", "titan", ",", "[[", "Covidien", "]]", ",", "to", "Massachusetts", "in", "April", ".", "This", "medical-supplies", "manufacturer", ",", "boasting", "over", "[[", "43,000", "]]", "employees", "and", "an", "extensive", "product", "line", ",", "will", "bring", "significant", "growth", "to", "the", "region", "."], "head_ent": ["Covidien"], "tail_ent": ["43,000"], "id": "org:number_of_employees--members_3_13"}, {"encoded_sent": [], "head_ent_type": "ORGANIZATION", "tail_ent_type": "NUMBER", "rewrited_sent": ["[[", "IPSCO's", "]]", "workforce", ",", "comprising", "approximately", "[[", "4,400", "]]", "individuals", ",", "experienced", "a", "27", "percent", "decline", "in", "first-quarter", "net", "profit", "to", "$1094", "million", "due", "to", "escalating", "expenses", ".", "Despite", "this", "setback", ",", "the", "company", "managed", "to", "record", "a", "14", "percent", "increase", "in", "sales", "during", "the", "same", "period", ",", "reaching", "a", "total", "revenue", "of", "$103", "billion", "."], "head_ent": ["IPSCO"], "tail_ent": ["4,400"], "id": "org:number_of_employees--members_3_14"}, {"encoded_sent": [], "head_ent_type": "ORGANIZATION", "tail_ent_type": "NUMBER", "rewrited_sent": ["[[", "Ownit", "Mortgage", "Solutions", "]]", ",", "an", "Agoura", "Hills-based", "company", ",", "filed", "for", "bankruptcy", "protection", "after", "laying", "off", "almost", "all", "of", "its", "[[", "800", "]]", "employees", "in", "December", ".", "This", "unfortunate", "event", "marked", "the", "beginning", "of", "shutdowns", "in", "the", "subprime", "sector", ".", "Notable", "companies", "like", "Fremont", "and", "New", "Century", "have", "also", "followed", "suit", ",", "contributing", "to", "the", "general", "downward", "trend", "in", "this", "industry", "."], "head_ent": ["Ownit", "Mortgage", "Solutions"], "tail_ent": ["800"], "id": "org:number_of_employees--members_3_15"}, {"encoded_sent": [], "head_ent_type": "ORGANIZATION", "tail_ent_type": "NUMBER", "rewrited_sent": ["At", "the", "Central", "American", "Parliament", ",", "a", "gathering", "of", "the", "[[", "Central", "American", "Nations", "]]", "in", "Guatemala", "City", ",", "D'Aubuisson", "and", "other", "Salvadoran", "politicians", "were", "in", "attendance", ".", "This", "parliament", "comprises", "[[", "132", "]]", "members", "."], "head_ent": ["Central", "American", "Parliament"], "tail_ent": ["132"], "id": "org:number_of_employees--members_3_16"}, {"encoded_sent": [], "head_ent_type": "ORGANIZATION", "tail_ent_type": "NUMBER", "rewrited_sent": ["Two", "entities", "are", "integral", "to", "the", "formation", "of", "the", "[[", "ADB", "]]", ":", "it", "was", "established", "in", "1966", "with", "the", "participation", "of", "31", "[[", "member", "governments", "]]", ".", "The", "primary", "sources", "of", "funding", "for", "the", "ADB", "consist", "of", "bonds", "and", "contributions", "from", "these", "governments", "."], "head_ent": ["ADB"], "tail_ent": ["31"], "id": "org:number_of_employees--members_3_17"}, {"encoded_sent": [], "head_ent_type": "ORGANIZATION", "tail_ent_type": "NUMBER", "rewrited_sent": ["A", "midlevel", "officer", "from", "Pakistan's", "leading", "intelligence", "agency", ",", "the", "Directorate", "for", "Inter-Services", "Intelligence", ",", "estimates", "that", "the", "membership", "of", "[[", "Lashkar-e-Taiba", "]]", "comprises", "approximately", "[[", "150,000", "]]", "individuals", "."], "head_ent": ["Lashkar-e-Taiba"], "tail_ent": ["150,000"], "id": "org:number_of_employees--members_3_18"}, {"encoded_sent": [], "head_ent_type": "ORGANIZATION", "tail_ent_type": "NUMBER", "rewrited_sent": ["[[", "Sixty", "thousand", "employees", "of", "ITW", "]]", ",", "working", "in", "52", "countries", ",", "will", "acquire", "a", "company", "through", "[[", "FNI", "Ltd", ".", "]]", ",", "a", "completely", "owned", "subsidiary", "of", "ITW", "."], "head_ent": ["ITW"], "tail_ent": ["60,000"], "id": "org:number_of_employees--members_3_19"}, {"encoded_sent": [], "head_ent_type": "ORGANIZATION", "tail_ent_type": "NUMBER", "rewrited_sent": ["The", "energy", ",", "agricultural", "and", "transportation", "equipment", "and", "construction", "industries", "rely", "on", "[[", "IPSCO", "]]", "for", "their", "steel", "needs", ",", "with", "this", "entity", "employing", "approximately", "[[", "4,300", "]]", "individuals", "and", "producing", "over", "4", "million", "tons", "of", "steel", "annually", "."], "head_ent": ["IPSCO"], "tail_ent": ["4,300"], "id": "org:number_of_employees--members_3_20"}, {"encoded_sent": [], "head_ent_type": "ORGANIZATION", "tail_ent_type": "NUMBER", "rewrited_sent": ["The", "request", "emerged", "during", "the", "deliberations", "of", "the", "[[", "Nuclear", "Suppliers", "Group", "]]", ",", "comprising", "of", "[[", "45", "]]", "members", ",", "on", "whether", "to", "sanction", "a", "deal", "enabling", "the", "US", "to", "supply", "India", "with", "civilian", "nuclear", "fuel", "and", "technology", "."], "head_ent": ["Nuclear", "Suppliers", "Group"], "tail_ent": ["45"], "id": "org:number_of_employees--members_3_21"}, {"encoded_sent": [], "head_ent_type": "ORGANIZATION", "tail_ent_type": "NUMBER", "rewrited_sent": ["Two", "prominent", "entities", "are", "featured", "in", "this", "sentence", ":", "Fyffes", "and", "approximately", "4,800", "employees", ".", "With", "a", "rich", "history", "dating", "back", "to", "a", "London", "banana", "importer", "in", "the", "late", "1800s", ",", "[[", "Fyffes", "]]", "has", "grown", "into", "one", "of", "the", "most", "significant", "tropical", "fruit", "importers", "into", "Europe", ".", "Simultaneously", ",", "this", "enterprise", "engages", "over", "[[", "4,800", "]]", "individuals", "across", "11", "different", "nations", "."], "head_ent": ["Fyffes"], "tail_ent": ["4,800"], "id": "org:number_of_employees--members_3_22"}, {"encoded_sent": [], "head_ent_type": "ORGANIZATION", "tail_ent_type": "NUMBER", "rewrited_sent": ["Late", "last", "month", ",", "the", "draft", "proposal", "remained", "unresolved", "among", "the", "[[", "45-members", "]]", ",", "leading", "the", "[[", "NSG", "]]", "to", "reconvene", "in", "Vienna", "with", "the", "intent", "to", "bridge", "their", "disparities", "concerning", "the", "approval", "of", "nuclear", "fuel", "and", "technology", "exports", "to", "India", "for", "civilian", "purposes", "."], "head_ent": ["NSG"], "tail_ent": ["45-member"], "id": "org:number_of_employees--members_3_23"}, {"encoded_sent": [], "head_ent_type": "ORGANIZATION", "tail_ent_type": "NUMBER", "rewrited_sent": ["[[", "Denso", "Corp", "]]", ",", "an", "automobile", "component", "supplier", "for", "Honda", ",", "Toyota", ",", "and", "other", "Japanese", "motor", "companies", ",", "based", "in", "Guangzhou's", "Nansha", "District", "since", "2004", ",", "employs", "approximately", "[[", "1,200", "]]", "individuals", "in", "their", "industrial", "complex", "."], "head_ent": ["Denso", "Corp"], "tail_ent": ["1,200"], "id": "org:number_of_employees--members_3_24"}, {"encoded_sent": [], "head_ent_type": "ORGANIZATION", "tail_ent_type": "NUMBER", "rewrited_sent": ["In", "Ireland", ",", "[[", "Covidien", "]]", "operates", "five", "factories", "and", "employs", "almost", "[[", "2,000", "]]", "people", ",", "contrasting", "the", "scenario", "in", "Bermuda", "where", "they", "only", "have", "a", "team", "of", "five", "employees", "."], "head_ent": ["Covidien"], "tail_ent": ["2,000"], "id": "org:number_of_employees--members_3_25"}, {"encoded_sent": [], "head_ent_type": "ORGANIZATION", "tail_ent_type": "NUMBER", "rewrited_sent": ["[[", "NS", "Group", "Inc", ".", "]]", "was", "acquired", "by", "[[", "IPSCO", "]]", ",", "a", "company", "with", "approximately", "4,400", "employees", ",", "for", "$1.43", "billion", "in", "cash", "in", "December", "."], "head_ent": ["IPSCO"], "tail_ent": ["4,400"], "id": "org:number_of_employees--members_3_26"}, {"encoded_sent": [], "head_ent_type": "ORGANIZATION", "tail_ent_type": "NUMBER", "rewrited_sent": ["The", "plant", "run", "by", "[[", "Denso", "]]", ",", "with", "a", "workforce", "of", "[[", "1,100", "]]", "employees", ",", "manufactures", "fuel", "injectors", "for", "engines", "."], "head_ent": ["Denso"], "tail_ent": ["1,100"], "id": "org:number_of_employees--members_3_27"}, {"encoded_sent": [], "head_ent_type": "ORGANIZATION", "tail_ent_type": "NUMBER", "rewrited_sent": ["The", "countries", "that", "making", "up", "the", "[[", "NSG", "]]", "with", "the", "[[", "45", "]]", "membership", "have", "planned", "to", "reconvene", "on", "Sept", ".", "4-5", "with", "the", "intent", "of", "resolving", "their", "disagreement", "regarding", "the", "permissibility", "of", "nuclear", "fuel", "and", "technology", "exports", "to", "India", "for", "peaceful", "purposes", "."], "head_ent": ["NSG"], "tail_ent": ["45"], "id": "org:number_of_employees--members_3_28"}, {"encoded_sent": [], "head_ent_type": "ORGANIZATION", "tail_ent_type": "NUMBER", "rewrited_sent": ["[[", "Sixty", "thousand", "employees", "]]", "of", "[[", "ITW", "]]", ",", "operating", "in", "52", "nations", ",", "will", "complete", "the", "acquisition", "utilizing", "FNI", "Ltd", ",", "a", "completely", "owned", "affiliate", "."], "head_ent": ["ITW"], "tail_ent": ["60,000"], "id": "org:number_of_employees--members_3_29"}, {"encoded_sent": [], "head_ent_type": "ORGANIZATION", "tail_ent_type": "NUMBER", "rewrited_sent": ["[[", "2,900", "]]", "individuals", "are", "employed", "by", "the", "[[", "company", "]]", "."], "head_ent": ["company"], "tail_ent": ["2,900"], "id": "org:number_of_employees--members_3_30"}, {"encoded_sent": [], "head_ent_type": "ORGANIZATION", "tail_ent_type": "NUMBER", "rewrited_sent": ["The", "severity", "and", "prevalence", "of", "this", "issue", "are", "such", "that", "the", "latest", "court", "decision", "to", "permit", "executions", "could", "sadly", "marks", "a", "regrettable", "mistake", "for", "the", "[[", "ABA", "]]", ",", "representing", "[[", "400,000", "]]", "members", "."], "head_ent": ["ABA"], "tail_ent": ["400,000"], "id": "org:number_of_employees--members_3_31"}, {"encoded_sent": [], "head_ent_type": "ORGANIZATION", "tail_ent_type": "NUMBER", "rewrited_sent": ["In", "Massachusetts", ",", "[[", "Covidien", "]]", "employs", "approximately", "2,000", "individuals", ",", "while", "its", "global", "workforce", "comprises", "around", "[[", "42,000", "]]", "people", "."], "head_ent": ["Covidien"], "tail_ent": ["42,000"], "id": "org:number_of_employees--members_3_32"}, {"encoded_sent": [], "head_ent_type": "ORGANIZATION", "tail_ent_type": "NUMBER", "rewrited_sent": ["With", "a", "global", "workforce", "of", "[[", "46,500", "]]", "and", "over", "12,700", "employees", "in", "Massachusetts", ",", "the", "[[", "company", "]]", "ranks", "among", "the", "region's", "largest", "employers", "as", "of", "the", "end", "of", "December", "."], "head_ent": ["company"], "tail_ent": ["46,500"], "id": "org:number_of_employees--members_3_33"}, {"encoded_sent": [], "head_ent_type": "ORGANIZATION", "tail_ent_type": "NUMBER", "rewrited_sent": ["Worldwide", ",", "[[", "14,000", "]]", "employees", "are", "part", "of", "[[", "It", "]]", "in", "New", "York", ",", "as", "of", "January", "16", ",", "2007", ",", "11:19", "p.m", ".", "UTC", "."], "head_ent": ["It"], "tail_ent": ["14,000"], "id": "org:number_of_employees--members_3_34"}, {"encoded_sent": [], "head_ent_type": "ORGANIZATION", "tail_ent_type": "NUMBER", "rewrited_sent": ["The", "[[", "Independent", "Steelworkers", "Union", "]]", ",", "which", "represents", "approximately", "1,250", "workers", "at", "Mittal", "Steel", "Co's", "mill", "in", "Weirton", ",", "West", "Virginia", ",", "announced", "its", "elected", "officials", "'", "decision", "to", "endorse", "a", "merger", "with", "the", "[[", "West", "Virginia", "steel", "industry", "labor", "union", "]]", "affiliated", "with", "the", "United", "Steelworkers", "(USW)", ",", "based", "in", "Pittsburgh", ",", "on", "Tuesday", "."], "head_ent": ["Independent", "Steelworkers", "Union"], "tail_ent": ["1,250"], "id": "org:number_of_employees--members_3_35"}]